myhumbleself/__init__.py
myhumbleself/app.py
myhumbleself/camera.py
myhumbleself/config.py
myhumbleself/converters.py
myhumbleself/face_detection.py
myhumbleself/structures.py
myhumbleself/video_handler.py
myhumbleself/resources/LICENSE
myhumbleself/resources/demo.mp4
myhumbleself/resources/face_detection_yunet_2023mar_int8.onnx
myhumbleself/resources/fallback.png
myhumbleself/resources/myhumbleself.gresource
MyHumbleSelf-0.1.1.dist-info/LICENSE
MyHumbleSelf-0.1.1.dist-info/METADATA
MyHumbleSelf-0.1.1.dist-info/WHEEL
MyHumbleSelf-0.1.1.dist-info/entry_points.txt
MyHumbleSelf-0.1.1.dist-info/top_level.txt
MyHumbleSelf-0.1.1.dist-info/RECORD
