Metadata-Version: 2.1
Name: MyHumbleSelf
Version: 0.1.1
Summary: Show your webcam image on the desktop for presentations.
Author-email: dynobo <dynobo@mailbox.org>
Project-URL: Source, https://github.com/dynobo/myhumbleself
Keywords: webcam,camera,utility,tool,presentation,screencast
Classifier: Development Status :: 4 - Beta
Classifier: License :: OSI Approved :: MIT License
Classifier: Programming Language :: Python
Classifier: Programming Language :: Python :: 3.10
Classifier: Programming Language :: Python :: 3.11
Classifier: Programming Language :: Python :: 3.12
Classifier: Programming Language :: Python :: Implementation :: CPython
Classifier: Programming Language :: Python :: Implementation :: PyPy
Classifier: Topic :: Utilities
Classifier: Intended Audience :: End Users/Desktop
Classifier: Operating System :: POSIX :: Linux
Requires-Python: >=3.10
License-File: LICENSE
Requires-Dist: PyGObject ==3.48.2
Requires-Dist: opencv-python-headless ==4.10.0.84
Provides-Extra: dev
Requires-Dist: build ==1.2.1 ; extra == 'dev'
Requires-Dist: mypy ==1.11.1 ; extra == 'dev'
Requires-Dist: opencv-stubs ==0.0.10 ; extra == 'dev'
Requires-Dist: pre-commit ==3.8.0 ; extra == 'dev'
Requires-Dist: pytest ==8.3.2 ; extra == 'dev'
Requires-Dist: pytest-cov ==5.0.0 ; extra == 'dev'
Requires-Dist: pytest-xvfb ==3.0.0 ; extra == 'dev'
Requires-Dist: ruff ==0.5.5 ; extra == 'dev'
Requires-Dist: pydeps ==1.12.20 ; extra == 'dev'
Requires-Dist: code2flow ==2.5.1 ; extra == 'dev'
Requires-Dist: tbump ==6.11.0 ; extra == 'dev'
